.gitignore
LICENSE
readme.md
setup.py
tests/__init__.py
tests/test_vlsir.py
vlsir/__init__.py
vlsir/circuit_pb2.py
vlsir/geometry_pb2.py
vlsir/netlist_pb2.py
vlsir/raw_pb2.py
vlsir/spice_pb2.py
vlsir/tech_pb2.py
vlsir/tetris_pb2.py
vlsir/utils_pb2.py
vlsir.egg-info/PKG-INFO
vlsir.egg-info/SOURCES.txt
vlsir.egg-info/dependency_links.txt
vlsir.egg-info/requires.txt
vlsir.egg-info/top_level.txt