Metadata-Version: 2.1
Name: vlsir
Version: 7.0.0
Summary: Python Bindings to the VLSIR Data Schemas for Chip Design
Home-page: https://github.com/Vlsir/Vlsir
Author: Dan Fritchman
Author-email: dan@fritch.mn
Requires-Python: >=3.7
Provides-Extra: dev
License-File: LICENSE
